emb/__init__.py
emb/_emb.py
emb-0.0.2.dist-info/LICENSE
emb-0.0.2.dist-info/WHEEL
emb-0.0.2.dist-info/METADATA
emb-0.0.2.dist-info/RECORD
