Metadata-Version: 2.1
Name: emb
Version: 0.0.2
Summary: Declarative library for for describing embedded C data types in python
Home-page: https://github.com/shawwn/emb
License: MIT
Author: csaba.nemes
Author-email: waszil.waszil@gmail.com
Requires-Python: >=3.6,<4.0
Classifier: License :: OSI Approved :: MIT License
Classifier: Programming Language :: Python :: 3
Classifier: Programming Language :: Python :: 3.6
Classifier: Programming Language :: Python :: 3.7
Classifier: Programming Language :: Python :: 3.8
Classifier: Programming Language :: Python :: 3.9
Classifier: Programming Language :: Python :: 3.10
Requires-Dist: get-annotations (>=0.1.2,<0.2.0)
